python_packaging_at/__init__.py
python_packaging_at/maths.py
python_packaging_at-0.6.0.dist-info/LICENSE
python_packaging_at-0.6.0.dist-info/METADATA
python_packaging_at-0.6.0.dist-info/WHEEL
python_packaging_at-0.6.0.dist-info/top_level.txt
python_packaging_at-0.6.0.dist-info/RECORD
